<?xml version="1.0"?>
<DataBase xmlns:xsd="http://www.w3.org/2001/XMLSchema" xmlns:xsi="http://www.w3.org/2001/XMLSchema-instance">
  <First_Dataset>
    <FirstDataset>
      <name>Level</name>
      <value>0</value>
    </FirstDataset>
    <FirstDataset>
      <name>Sound</name>
      <value>0.5259019</value>
    </FirstDataset>
    <FirstDataset>
      <name>Score_Lvl1</name>
      <value>0</value>
    </FirstDataset>
    <FirstDataset>
      <name>Score_Lvl2</name>
      <value>0</value>
    </FirstDataset>
    <FirstDataset>
      <name>Score_Lvl3</name>
      <value>0</value>
    </FirstDataset>
    <FirstDataset>
      <name>Score_Lvl4</name>
      <value>0</value>
    </FirstDataset>
    <FirstDataset>
      <name>Score_Lvl5</name>
      <value>0</value>
    </FirstDataset>
  </First_Dataset>
  <Second_Dataset />
</DataBase>